typalizer/__init__.py
typalizer-0.0.14.dist-info/LICENSE
typalizer-0.0.14.dist-info/METADATA
typalizer-0.0.14.dist-info/WHEEL
typalizer-0.0.14.dist-info/top_level.txt
typalizer-0.0.14.dist-info/RECORD
