Metadata-Version: 2.1
Name: typalizer
Version: 0.0.14
Summary: Type Analysis tool for Pandas DataFrames
Home-page: UNKNOWN
Author: Mursil Khan
Author-email: <mursilkhan30@gmail.com>
License: UNKNOWN
Keywords: python,data,analysis,type analysis,pandas,dataframes
Platform: UNKNOWN
Classifier: Development Status :: 1 - Planning
Classifier: Programming Language :: Python :: 3
Classifier: Operating System :: Unix
Classifier: Operating System :: MacOS :: MacOS X
Classifier: Operating System :: Microsoft :: Windows
License-File: LICENSE
Requires-Dist: pandas
